{
  "unknown_threshold": 0.55,
  "labelmap": {
    "0": "person_0000",
    "1": "person_0001",
    "2": "person_0002",
    "3": "person_0003",
    "4": "person_0004",
    "5": "person_0005",
    "6": "person_0006",
    "7": "person_0007",
    "8": "person_0008",
    "9": "person_0009",
    "10": "person_0010",
    "11": "person_0011",
    "12": "person_0012",
    "13": "person_0013",
    "14": "person_0014",
    "15": "person_0015",
    "16": "person_0016",
    "17": "person_0017",
    "18": "person_0018",
    "19": "person_0019",
    "20": "person_0020",
    "21": "person_0021",
    "22": "person_0022",
    "23": "person_0023",
    "24": "person_0024",
    "25": "person_0025",
    "26": "person_0026",
    "27": "person_0027",
    "28": "person_0028",
    "29": "person_0029",
    "30": "person_0030",
    "31": "person_0031",
    "32": "person_0032",
    "33": "person_0033",
    "34": "person_0034",
    "35": "person_0035",
    "36": "person_0036",
    "37": "person_0037",
    "38": "person_0038",
    "39": "person_0039",
    "40": "person_0040",
    "41": "person_0041",
    "42": "person_0042",
    "43": "person_0043",
    "44": "person_0044",
    "45": "person_0045",
    "46": "person_0046",
    "47": "person_0047",
    "48": "person_0048",
    "49": "person_0049",
    "50": "person_0050",
    "51": "person_0051",
    "52": "person_0052",
    "53": "person_0053",
    "54": "person_0054",
    "55": "person_0055",
    "56": "person_0056",
    "57": "person_0057",
    "58": "person_0058",
    "59": "person_0059",
    "60": "person_0060",
    "61": "person_0061",
    "62": "person_0062",
    "63": "person_0063",
    "64": "person_0064",
    "65": "person_0065",
    "66": "person_0066",
    "67": "person_0067",
    "68": "person_0068",
    "69": "person_0069",
    "70": "person_0070",
    "71": "person_0071",
    "72": "person_0072",
    "73": "person_0073",
    "74": "person_0074",
    "75": "person_0075",
    "76": "person_0076",
    "77": "person_0077",
    "78": "person_0078",
    "79": "person_0079",
    "80": "person_0080",
    "81": "person_0081",
    "82": "person_0082",
    "83": "person_0083",
    "84": "person_0084",
    "85": "person_0085",
    "86": "person_0086",
    "87": "person_0087",
    "88": "person_0088",
    "89": "person_0089",
    "90": "person_0090",
    "91": "person_0091",
    "92": "person_0092",
    "93": "person_0093",
    "94": "person_0094",
    "95": "person_0095",
    "96": "person_0096",
    "97": "person_0097",
    "98": "person_0098",
    "99": "person_0099",
    "100": "person_0100",
    "101": "person_0101",
    "102": "person_0102",
    "103": "person_0103",
    "104": "person_0104",
    "105": "person_0105",
    "106": "person_0106",
    "107": "person_0107",
    "108": "person_0108",
    "109": "person_0109",
    "110": "person_0110",
    "111": "person_0111",
    "112": "person_0112",
    "113": "person_0113",
    "114": "person_0114",
    "115": "person_0115",
    "116": "person_0116",
    "117": "person_0117",
    "118": "person_0118",
    "119": "person_0119",
    "120": "person_0120",
    "121": "person_0121",
    "122": "person_0122",
    "123": "person_0123",
    "124": "person_0124",
    "125": "person_0125",
    "126": "person_0126",
    "127": "person_0127"
  },
  "best_params": {
    "C": 5,
    "gamma": "scale",
    "kernel": "rbf"
  },
  "val_accuracy": 0.9897959183673469,
  "embedding": "FaceNet-128D-L2"
}